anton_cli/__init__.py
anton_cli/cli.py
anton_cli/collect_framework.py
anton_cli/words.txt
anton_cli-1.0.0.dist-info/WHEEL
anton_cli-1.0.0.dist-info/METADATA
anton_cli-1.0.0.dist-info/RECORD
