Metadata-Version: 2.1
Name: anton-cli
Version: 1.0.0
Summary: Returns the number of unique characters in the string
License: MIT
Author: Skazko Anton
Author-email: sk.anton06@gmail.com
Requires-Python: >=3.8,<4.0
Classifier: License :: OSI Approved :: MIT License
Classifier: Programming Language :: Python :: 3
Classifier: Programming Language :: Python :: 3.10
Classifier: Programming Language :: Python :: 3.8
Classifier: Programming Language :: Python :: 3.9
